hierarchical_confusion_matrix/HierarchicalConfusion.py
hierarchical_confusion_matrix/__init__.py
hierarchical_confusion_matrix-1.0.3.dist-info/LICENSE
hierarchical_confusion_matrix-1.0.3.dist-info/METADATA
hierarchical_confusion_matrix-1.0.3.dist-info/WHEEL
hierarchical_confusion_matrix-1.0.3.dist-info/top_level.txt
hierarchical_confusion_matrix-1.0.3.dist-info/RECORD
