Metadata-Version: 2.1
Name: hierarchical-confusion-matrix
Version: 1.0.3
Summary: Hierarchical Confusion Matrix - a novel measure for evaluation of any hierarchical classification problem
Author: Kevin Riehl
Project-URL: Homepage, https://github.com/DerKevinRiehl/HierarchicalConfusionMatrix/
Project-URL: Bug Tracker, https://github.com/DerKevinRiehl/HierarchicalConfusionMatrix/issues
Classifier: Programming Language :: Python :: 3
Classifier: License :: OSI Approved :: MIT License
Classifier: Operating System :: OS Independent
Requires-Python: >=3.7
License-File: LICENSE
